Metadata-Version: 1.1
Name: flextable
Version: 1.0.43
Summary: UNKNOWN
Home-page: https://github.com/chris17453/flextable/
Author: Charles Watkins
Author-email: charles@titandws.com
License: Creative Commons Attribution-Noncommercial-Share Alike license
Platform: UNKNOWN
Classifier: Programming Language :: Python :: 2.7
Classifier: Programming Language :: Python :: 3.7
